django_substitution_user-0.1.3.dist-info/DESCRIPTION.rst
django_substitution_user-0.1.3.dist-info/METADATA
django_substitution_user-0.1.3.dist-info/metadata.json
django_substitution_user-0.1.3.dist-info/RECORD
django_substitution_user-0.1.3.dist-info/top_level.txt
django_substitution_user-0.1.3.dist-info/WHEEL
substitution_user/__init__.py
substitution_user/admin.py
substitution_user/middleware.py
substitution_user/urls.py
substitution_user/views.py
substitution_user/templatetags/__init__.py
substitution_user/templatetags/substitution_user.py
