Metadata-Version: 2.0
Name: django-substitution-user
Version: 0.1.3
Summary: Django substitution user
Home-page: https://github.com/torchingloom/django-substitution-user
Author: Alexey Baranov
Author-email: atlantij@gmail.com
License: UNKNOWN
Platform: UNKNOWN
Classifier: Environment :: Web Environment
Classifier: Intended Audience :: Developers
Classifier: Operating System :: OS Independent
Classifier: Programming Language :: Python
Classifier: Programming Language :: Python :: 2
Classifier: Programming Language :: Python :: 2.7
Classifier: Framework :: Django
